<h:html xmlns="http://www.w3.org/2002/xforms" xmlns:h="http://www.w3.org/1999/xhtml" xmlns:ev="http://www.w3.org/2001/xml-events" xmlns:xsd="http://www.w3.org/2001/XMLSchema" xmlns:jr="http://openrosa.org/javarosa">
  <h:head>
    <h:title>Tendai Patient</h:title>
    <model>
      <instance>
        <data id="build_Tendai-Patient_1316685641">
          <form_version>0.1</form_version>

          <start_time/>
          <end_time/>
          <survey_date/>
          <device_id/>
          <subscriber_id/>
          <sim_id/>
          <phone_number/>

          <patient_name/>
          <patient_availability/>
          <patients_availability2/>
          <patient_where/>
          <patient_where_other/>
          <patient_affordability/>
          <patient_costs/>
          <patient_income_perc/>
          <patient_photo/>
          <patient_story/>
          <patient_audio/>
          <patient_comments/>
        </data>
      </instance>
      <itext>
        <translation lang="eng">
          <text id="/data/patient_name:label">
            <value>Patient Name</value>
          </text>
          <text id="/data/patient_name:hint">
            <value>This can be a full name or simply a first name</value>
          </text>
          <text id="/data/patient_availability:label">
            <value>General Availability of medicines</value>
          </text>
          <text id="/data/patient_availability:hint">
            <value>Please ask the patient to comment on the general availability of medicines at this facility</value>
          </text>
          <text id="/data/patients_availability2:label">
            <value>How would you rate medicine availability?</value>
          </text>
          <text id="/data/patients_availability2:hint">
            <value/>
          </text>
          <text id="/data/patients_availability2:option0">
            <value>Always Available</value>
          </text>
          <text id="/data/patients_availability2:option1">
            <value>Sometimes Available</value>
          </text>
          <text id="/data/patients_availability2:option2">
            <value>Seldom Available</value>
          </text>
          <text id="/data/patients_availability2:option3">
            <value>Never Available</value>
          </text>
          <text id="/data/patient_where:label">
            <value>Where do you usually get your medicines</value>
          </text>
          <text id="/data/patient_where:hint">
            <value/>
          </text>
          <text id="/data/patient_where:option0">
            <value>Government Facility</value>
          </text>
          <text id="/data/patient_where:option1">
            <value>Private Pharmacy</value>
          </text>
          <text id="/data/patient_where:option2">
            <value>Mission Facility</value>
          </text>
          <text id="/data/patient_where:option3">
            <value>NGO Facility</value>
          </text>
          <text id="/data/patient_where:option4">
            <value>Other</value>
          </text>
          <text id="/data/patient_where_other:label">
            <value>Please specify where you get your medicines</value>
          </text>
          <text id="/data/patient_where_other:hint">
            <value/>
          </text>
          <text id="/data/patient_affordability:label">
            <value>Do you consider essential medicines at this facility to be affordable?</value>
          </text>
          <text id="/data/patient_affordability:hint">
            <value/>
          </text>
          <text id="/data/patient_affordability:option0">
            <value>Medicines are free</value>
          </text>
          <text id="/data/patient_affordability:option1">
            <value>Always affordable</value>
          </text>
          <text id="/data/patient_affordability:option2">
            <value>Sometimes affordable</value>
          </text>
          <text id="/data/patient_affordability:option3">
            <value>Never affordable</value>
          </text>
          <text id="/data/patient_costs:label">
            <value>What other costs do you incur for you to access medicines?</value>
          </text>
          <text id="/data/patient_costs:hint">
            <value/>
          </text>
          <text id="/data/patient_costs:option0">
            <value>Transport</value>
          </text>
          <text id="/data/patient_costs:option1">
            <value>Accommodation</value>
          </text>
          <text id="/data/patient_costs:option2">
            <value>Food</value>
          </text>
          <text id="/data/patient_costs:option3">
            <value>Other Fees</value>
          </text>
          <text id="/data/patient_costs:option4">
            <value>Other</value>
          </text>
          <text id="/data/patient_income_perc:label">
            <value>What percentage of your monthly income do you spend on medicines?</value>
          </text>
          <text id="/data/patient_income_perc:hint">
            <value/>
          </text>
          <text id="/data/patient_income_perc:option0">
            <value>0-5%</value>
          </text>
          <text id="/data/patient_income_perc:option1">
            <value>6-10%</value>
          </text>
          <text id="/data/patient_income_perc:option2">
            <value>11-20%</value>
          </text>
          <text id="/data/patient_income_perc:option3">
            <value>21-30%</value>
          </text>
          <text id="/data/patient_income_perc:option4">
            <value>31-50%</value>
          </text>
          <text id="/data/patient_income_perc:option5">
            <value>51-70%</value>
          </text>
          <text id="/data/patient_income_perc:option6">
            <value>71-100%</value>
          </text>
          <text id="/data/patient_income_perc:option7">
            <value>more than 100%</value>
          </text>
          <text id="/data/patient_photo:label">
            <value>Photo</value>
          </text>
          <text id="/data/patient_photo:hint">
            <value>With the patient's permission, take a photo of their face. Include shoulders and hair</value>
          </text>
          <text id="/data/patient_story:label">
            <value>Patient Story</value>
          </text>
          <text id="/data/patient_story:hint">
            <value>Ask the patient to describe a good or bad experience they have had trying to purchase medicines (approx 200 words)</value>
          </text>
          <text id="/data/patient_audio:label">
            <value>Audio Recording</value>
          </text>
          <text id="/data/patient_audio:hint">
            <value>You may record the patients story if you think it may be useful to hear it spoken. Please make sure that the patient is close to the phone when they talk. Also, please record for no more than 5 minutes.</value>
          </text>
          <text id="/data/patient_comments:label">
            <value>Comments</value>
          </text>
          <text id="/data/patient_comments:hint">
            <value>Please include any comments you might like to add about the patient that might be relevant to the story.</value>
          </text>
        </translation>
      </itext>
      <bind nodeset="/data/start_time" type="dateTime" jr:preload="timestamp" jr:preloadParams="start"/> 
      <bind nodeset="/data/end_time" type="dateTime" jr:preload="timestamp" jr:preloadParams="end"/> 
      <bind nodeset="/data/survey_date" type="date" jr:preload="today" jr:preloadParams="end"/> 
      <bind nodeset="/data/device_id" type="string" jr:preload="property" jr:preloadParams="deviceid"/> 
      <bind nodeset="/data/subscriber_id" type="string" jr:preload="property" jr:preloadParams="subscriberid"/> 
      <bind nodeset="/data/sim_id" type="string" jr:preload="property" jr:preloadParams="simserial"/>
      <bind nodeset="/data/phone_number" type="string" jr:preload="property" jr:preloadParams="phonenumber"/>

      <bind nodeset="/data/patient_name" type="string"/>
      <bind nodeset="/data/patient_availability" type="string"/>
      <bind nodeset="/data/patients_availability2" type="select1"/>
      <bind nodeset="/data/patient_where" type="select1"/>
      <bind nodeset="/data/patient_where_other" type="string" relevant="(/data/patient_where = 'other')"/>
      <bind nodeset="/data/patient_affordability" type="select1"/>
      <bind nodeset="/data/patient_costs" type="select"/>
      <bind nodeset="/data/patient_income_perc" type="select1"/>
      <bind nodeset="/data/patient_photo" type="binary"/>
      <bind nodeset="/data/patient_story" type="string"/>
      <bind nodeset="/data/patient_audio" type="binary"/>
      <bind nodeset="/data/patient_comments" type="string"/>
    </model>
  </h:head>
  <h:body>
    <input ref="/data/patient_name">
      <label ref="jr:itext('/data/patient_name:label')"/>
      <hint ref="jr:itext('/data/patient_name:hint')"/>
    </input>
    <input ref="/data/patient_availability">
      <label ref="jr:itext('/data/patient_availability:label')"/>
      <hint ref="jr:itext('/data/patient_availability:hint')"/>
    </input>
    <select1 ref="/data/patients_availability2">
      <label ref="jr:itext('/data/patients_availability2:label')"/>
      <hint ref="jr:itext('/data/patients_availability2:hint')"/>
      <item>
        <label ref="jr:itext('/data/patients_availability2:option0')"/>
        <value>always</value>
      </item>
      <item>
        <label ref="jr:itext('/data/patients_availability2:option1')"/>
        <value>sometimes</value>
      </item>
      <item>
        <label ref="jr:itext('/data/patients_availability2:option2')"/>
        <value>seldom</value>
      </item>
      <item>
        <label ref="jr:itext('/data/patients_availability2:option3')"/>
        <value>never</value>
      </item>
    </select1>
    <select1 ref="/data/patient_where">
      <label ref="jr:itext('/data/patient_where:label')"/>
      <hint ref="jr:itext('/data/patient_where:hint')"/>
      <item>
        <label ref="jr:itext('/data/patient_where:option0')"/>
        <value>government</value>
      </item>
      <item>
        <label ref="jr:itext('/data/patient_where:option1')"/>
        <value>private</value>
      </item>
      <item>
        <label ref="jr:itext('/data/patient_where:option2')"/>
        <value>mission</value>
      </item>
      <item>
        <label ref="jr:itext('/data/patient_where:option3')"/>
        <value>ngo</value>
      </item>
      <item>
        <label ref="jr:itext('/data/patient_where:option4')"/>
        <value>other</value>
      </item>
    </select1>
    <input ref="/data/patient_where_other">
      <label ref="jr:itext('/data/patient_where_other:label')"/>
      <hint ref="jr:itext('/data/patient_where_other:hint')"/>
    </input>
    <select1 ref="/data/patient_affordability">
      <label ref="jr:itext('/data/patient_affordability:label')"/>
      <hint ref="jr:itext('/data/patient_affordability:hint')"/>
      <item>
        <label ref="jr:itext('/data/patient_affordability:option0')"/>
        <value>free</value>
      </item>
      <item>
        <label ref="jr:itext('/data/patient_affordability:option1')"/>
        <value>always</value>
      </item>
      <item>
        <label ref="jr:itext('/data/patient_affordability:option2')"/>
        <value>sometimes</value>
      </item>
      <item>
        <label ref="jr:itext('/data/patient_affordability:option3')"/>
        <value>never</value>
      </item>
    </select1>
    <select ref="/data/patient_costs">
      <label ref="jr:itext('/data/patient_costs:label')"/>
      <hint ref="jr:itext('/data/patient_costs:hint')"/>
      <item>
        <label ref="jr:itext('/data/patient_costs:option0')"/>
        <value>transport</value>
      </item>
      <item>
        <label ref="jr:itext('/data/patient_costs:option1')"/>
        <value>accommodation</value>
      </item>
      <item>
        <label ref="jr:itext('/data/patient_costs:option2')"/>
        <value>food</value>
      </item>
      <item>
        <label ref="jr:itext('/data/patient_costs:option3')"/>
        <value>other_fees</value>
      </item>
      <item>
        <label ref="jr:itext('/data/patient_costs:option4')"/>
        <value>other</value>
      </item>
    </select>
    <select1 ref="/data/patient_income_perc">
      <label ref="jr:itext('/data/patient_income_perc:label')"/>
      <hint ref="jr:itext('/data/patient_income_perc:hint')"/>
      <item>
        <label ref="jr:itext('/data/patient_income_perc:option0')"/>
        <value>0-5</value>
      </item>
      <item>
        <label ref="jr:itext('/data/patient_income_perc:option1')"/>
        <value>6-10</value>
      </item>
      <item>
        <label ref="jr:itext('/data/patient_income_perc:option2')"/>
        <value>11-20</value>
      </item>
      <item>
        <label ref="jr:itext('/data/patient_income_perc:option3')"/>
        <value>21-30</value>
      </item>
      <item>
        <label ref="jr:itext('/data/patient_income_perc:option4')"/>
        <value>31-50</value>
      </item>
      <item>
        <label ref="jr:itext('/data/patient_income_perc:option5')"/>
        <value>51-70</value>
      </item>
      <item>
        <label ref="jr:itext('/data/patient_income_perc:option6')"/>
        <value>71-100</value>
      </item>
      <item>
        <label ref="jr:itext('/data/patient_income_perc:option7')"/>
        <value>100+</value>
      </item>
    </select1>
    <upload ref="/data/patient_photo" mediatype="image/*">
      <label ref="jr:itext('/data/patient_photo:label')"/>
      <hint ref="jr:itext('/data/patient_photo:hint')"/>
    </upload>
    <input ref="/data/patient_story">
      <label ref="jr:itext('/data/patient_story:label')"/>
      <hint ref="jr:itext('/data/patient_story:hint')"/>
    </input>
    <upload ref="/data/patient_audio" mediatype="audio/*">
      <label ref="jr:itext('/data/patient_audio:label')"/>
      <hint ref="jr:itext('/data/patient_audio:hint')"/>
    </upload>
    <input ref="/data/patient_comments">
      <label ref="jr:itext('/data/patient_comments:label')"/>
      <hint ref="jr:itext('/data/patient_comments:hint')"/>
    </input>
  </h:body>
</h:html>
